logmon/__init__.py
logmon/bot.py
logmon/commands_linux.py
logmon/config.py
logmon/init.py
logmon/main_executor.py
logmon/main_watcher.py
logmon/notify_loop.py
logmon-0.0.2.dist-info/METADATA
logmon-0.0.2.dist-info/WHEEL
logmon-0.0.2.dist-info/top_level.txt
logmon-0.0.2.dist-info/RECORD
