Metadata-Version: 2.1
Name: logmon
Version: 0.0.2
Summary: Linux authentication log monitor and commands executor
Author-email: DrEm-s <unfol2000@gmail.com>
Project-URL: Homepage, https://github.com/DrEm-s/logmonitor
Keywords: authentication,logs,monitoring,telegram
Requires-Python: >=3.8
Requires-Dist: certifi ==2024.6.2
Requires-Dist: charset-normalizer ==3.3.2
Requires-Dist: idna ==3.7
Requires-Dist: pyinotify-elephant-fork ==0.0.1
Requires-Dist: python-dotenv ==1.0.1
Requires-Dist: requests ==2.32.3
Requires-Dist: urllib3 ==2.2.1
